{
  "name": "ChatChannelService Demo",
  "tree": {
    "$className": "DataModel",

    "ReplicatedStorage": {
      "ChatChannelService": {
        "$path": "./src",

        "Modules": {
          "$className": "Folder",

          "Icon": {
            "$path": "./modules/TopbarPlus/withoutLink.project.json"
          }
        }
      }
    },

    "ServerScriptService": {
      "$path": "./demo/server"
    },

    "StarterPlayer": {
      "StarterPlayerScripts": {
        "$path": "./demo/client"
      }
    }
  }
}
